midanki/__init__.py
midanki/cli.py
midanki/midanki.py
midanki-0.1.0.dist-info/AUTHORS.rst
midanki-0.1.0.dist-info/LICENSE
midanki-0.1.0.dist-info/METADATA
midanki-0.1.0.dist-info/WHEEL
midanki-0.1.0.dist-info/entry_points.txt
midanki-0.1.0.dist-info/top_level.txt
midanki-0.1.0.dist-info/RECORD
