Metadata-Version: 2.1
Name: midanki
Version: 0.1.0
Summary: Converts midi input to keyboard input for anki reviews.
Home-page: https://github.com/j718/midanki
Author: Jacob Clarke
Author-email: jacobclarke718@gmail.com
License: MIT license
Keywords: midanki
Platform: UNKNOWN
Classifier: Development Status :: 2 - Pre-Alpha
Classifier: Intended Audience :: Developers
Classifier: License :: OSI Approved :: MIT License
Classifier: Natural Language :: English
Classifier: Programming Language :: Python :: 2
Classifier: Programming Language :: Python :: 2.7
Classifier: Programming Language :: Python :: 3
Classifier: Programming Language :: Python :: 3.5
Classifier: Programming Language :: Python :: 3.6
Classifier: Programming Language :: Python :: 3.7
Classifier: Programming Language :: Python :: 3.8
Requires-Python: >=2.7, !=3.0.*, !=3.1.*, !=3.2.*, !=3.3.*, !=3.4.*
Requires-Dist: Click (>=7.0)
Requires-Dist: pynput
Requires-Dist: pygame
